{
  "version": 1,
  "useShadows": true,
  "heightScale": 142,
  "shadowStrength": 0.75,
  "shadowBlur": 3,
  "ambient": 0.31,
  "diffuse": 0.92,
  "useVolumetric": false,
  "volumetricStrength": 0.24,
  "volumetricDensity": 0.85,
  "volumetricAnisotropy": 0.45,
  "volumetricLength": 52,
  "volumetricSamples": 12,
  "cycleHour": 10.77,
  "cycleSpeed": 0.01,
  "simTickHours": 0.01,
  "pointFlickerEnabled": false,
  "pointFlickerStrength": 0.55,
  "pointFlickerSpeed": 2.4,
  "pointFlickerSpatial": 1
}
